sier2_blocks_config/__init__.py
sier2_blocks_config-0.1.dist-info/entry_points.txt
sier2_blocks_config-0.1.dist-info/LICENSE
sier2_blocks_config-0.1.dist-info/METADATA
sier2_blocks_config-0.1.dist-info/WHEEL
sier2_blocks_config-0.1.dist-info/RECORD
