Metadata-Version: 2.3
Name: sier2-blocks-config
Version: 0.1
Summary: Configuration for sier2-blocks.
Author: Algol60
Author-email: algol60 <algol60@users.noreply.github.com>
Classifier: Programming Language :: Python :: 3.11
Classifier: Operating System :: OS Independent
Classifier: Intended Audience :: Science/Research
Classifier: Intended Audience :: Developers
Classifier: Topic :: Scientific/Engineering
Classifier: Topic :: Software Development :: Libraries
